wagtail_stacks_embed/__init__.py
wagtail_stacks_embed/apps.py
wagtail_stacks_embed/blocks.py
wagtail_stacks_embed/models.py
wagtail_stacks_embed/registered_blocks.py
wagtail_stacks_embed/registry.py
wagtail_stacks_embed/utils.py
wagtail_stacks_embed/migrations/0001_initial.py
wagtail_stacks_embed/migrations/0002_auto_20151002_1353.py
wagtail_stacks_embed/migrations/0003_auto_20151207_2047.py
wagtail_stacks_embed/migrations/__init__.py
wagtail_stacks_embed/pbs_cove/__init__.py
wagtail_stacks_embed/pbs_cove/stacks_embed_service.py
wagtail_stacks_embed/pbs_cove/static/js/passport.js
wagtail_stacks_embed/pbs_cove/static/sass/_passport.scss
wagtail_stacks_embed/soundcloud/__init__.py
wagtail_stacks_embed/soundcloud/stacks_embed_service.py
wagtail_stacks_embed/static/images/play-icon-hover.png
wagtail_stacks_embed/static/images/play-icon.png
wagtail_stacks_embed/static/js/wagtail_stacks_embed.js
wagtail_stacks_embed/static/sass/_wagtail_stacks_embed.scss
wagtail_stacks_embed/templates/wagtail_stacks_embed/list/1up.html
wagtail_stacks_embed/templates/wagtail_stacks_embed/list/2up.html
wagtail_stacks_embed/templates/wagtail_stacks_embed/list/3up.html
wagtail_stacks_embed/templates/wagtail_stacks_embed/list/carousel.html
wagtail_stacks_embed/templates/wagtail_stacks_embed/list/list-item-carousel.html
wagtail_stacks_embed/templates/wagtail_stacks_embed/list/list-item.html
wagtail_stacks_embed/templates/wagtail_stacks_embed/single/embed_left_content_right.html
wagtail_stacks_embed/templates/wagtail_stacks_embed/single/embed_right_content_left.html
wagtail_stacks_embed/templates/wagtail_stacks_embed/single/full_width.html
wagtail_stacks_embed/vimeo/__init__.py
wagtail_stacks_embed/vimeo/stacks_embed_service.py
wagtail_stacks_embed/youtube/__init__.py
wagtail_stacks_embed/youtube/stacks_embed_service.py
wagtail_stacks_embed-0.3.dist-info/DESCRIPTION.rst
wagtail_stacks_embed-0.3.dist-info/LICENSE.txt
wagtail_stacks_embed-0.3.dist-info/METADATA
wagtail_stacks_embed-0.3.dist-info/RECORD
wagtail_stacks_embed-0.3.dist-info/WHEEL
wagtail_stacks_embed-0.3.dist-info/metadata.json
wagtail_stacks_embed-0.3.dist-info/top_level.txt
